mathyBJS/__init__.py
mathyBJS/add.py
mathyBJS/ceil.py
mathyBJS/device_name.py
mathyBJS/div.py
mathyBJS/floor.py
mathyBJS/flr.py
mathyBJS/get_system.py
mathyBJS/hide_file.py
mathyBJS/logged_username.py
mathyBJS/main.py
mathyBJS/mod.py
mathyBJS/mult.py
mathyBJS/pow.py
mathyBJS/round.py
mathyBJS/spec_err.py
mathyBJS/sub.py
mathybjs-0.1.1.dist-info/METADATA
mathybjs-0.1.1.dist-info/WHEEL
mathybjs-0.1.1.dist-info/RECORD
