Metadata-Version: 2.4
Name: mathyBJS
Version: 0.1.1
Summary: NOTHING FOR NOW..
License: MIT
Author: BJS
Author-email: coderbjs@gmail.com
Requires-Python: >=3.13.7
Classifier: License :: OSI Approved :: MIT License
Classifier: Programming Language :: Python :: 3
Classifier: Programming Language :: Python :: 3.14
Requires-Dist: colorama (==0.4.6)
Requires-Dist: numpy (==2.3.5)
